README.md
setup.py
dynprops/__init__.py
dynprops/_dynprops.py
dynprops.egg-info/PKG-INFO
dynprops.egg-info/SOURCES.txt
dynprops.egg-info/dependency_links.txt
dynprops.egg-info/top_level.txt