Metadata-Version: 1.1
Name: dynprops
Version: 0.1.1
Summary: Dynamic Properties - support for complex tsv and sql values
Home-page: http://github.com/hsolbrig/dynprops
Author: Harold Solbrig
Author-email: solbrig@solbrig-informatics.com
License: Apache 2.0
Platform: UNKNOWN
Classifier: Development Status :: 3 - Alpha
Classifier: Environment :: Console
Classifier: Intended Audience :: Developers
Classifier: Topic :: Software Development :: Libraries
Classifier: Programming Language :: Python :: 3 :: Only
Classifier: Programming Language :: Python :: 3.6
